{"salt": "VN6pLiNQTsTiOjAVf/DboQ==", "iteraciones": 200000, "clips": [{"id": "ev1262", "tipo": "evidencia", "fecha": "2026-07-22", "hora": "2026-07-22T22:11:31.219701", "planta": "desconocida", "clase": "bloque_grande", "archivo": "clips/ev1262.enc", "iv": "J0uK/xSlbiA1ZNJm"}, {"id": "ev1258", "tipo": "evidencia", "fecha": "2026-07-22", "hora": "2026-07-22T20:05:04.331685", "planta": "desconocida", "clase": "bloque_grande", "archivo": "clips/ev1258.enc", "iv": "fZcC+i1FMPAN9Nf2"}, {"id": "ev1254", "tipo": "evidencia", "fecha": "2026-07-22", "hora": "2026-07-22T10:43:23.196618", "planta": "desconocida", "clase": "bloque_grande", "archivo": "clips/ev1254.enc", "iv": "RcOnB3J+7ck1+cYU"}, {"id": "ev1250", "tipo": "evidencia", "fecha": "2026-07-22", "hora": "2026-07-22T10:38:46.497886", "planta": "desconocida", "clase": "bloque_grande", "archivo": "clips/ev1250.enc", "iv": "QB5obJLZuXzVjWHB"}, {"id": "ev1246", "tipo": "evidencia", "fecha": "2026-07-22", "hora": "2026-07-22T10:32:22.504621", "planta": "desconocida", "clase": "bloque_grande", "archivo": "clips/ev1246.enc", "iv": "3DmHqvNzCqsyP39J"}, {"id": "ev1242", "tipo": "evidencia", "fecha": "2026-07-22", "hora": "2026-07-22T10:25:03.655524", "planta": "desconocida", "clase": "bloque_grande", "archivo": "clips/ev1242.enc", "iv": "nhKq2zcCnmRb4Hfr"}, {"id": "ev1238", "tipo": "evidencia", "fecha": "2026-07-22", "hora": "2026-07-22T10:20:00.933811", "planta": "desconocida", "clase": "bloque_grande", "archivo": "clips/ev1238.enc", "iv": "J3U5Vd72u3gxBsET"}, {"id": "ev1234", "tipo": "evidencia", "fecha": "2026-07-22", "hora": "2026-07-22T10:13:51.899262", "planta": "desconocida", "clase": "bloque_grande", "archivo": "clips/ev1234.enc", "iv": "DiDwWsvJ39zh9PPN"}, {"id": "ev1230", "tipo": "evidencia", "fecha": "2026-07-22", "hora": "2026-07-22T09:58:43.197670", "planta": "desconocida", "clase": "bloque_grande", "archivo": "clips/ev1230.enc", "iv": "oInUVT8y6MDpb+T6"}, {"id": "ev1226", "tipo": "evidencia", "fecha": "2026-07-22", "hora": "2026-07-22T09:51:44.647237", "planta": "desconocida", "clase": "bloque_grande", "archivo": "clips/ev1226.enc", "iv": "p7Hy5bK8GXV11KDT"}, {"id": "ev1222", "tipo": "evidencia", "fecha": "2026-07-22", "hora": "2026-07-22T09:44:58.643891", "planta": "desconocida", "clase": "bloque_grande", "archivo": "clips/ev1222.enc", "iv": "ZuKLvtXgJtEup5RO"}, {"id": "ev1210", "tipo": "evidencia", "fecha": "2026-07-22", "hora": "2026-07-22T08:51:26.045312", "planta": "desconocida", "clase": "bloque_grande", "archivo": "clips/ev1210.enc", "iv": "Jzf10VHXwkvqgX8a"}, {"id": "ev1202", "tipo": "evidencia", "fecha": "2026-07-22", "hora": "2026-07-22T08:46:10.735667", "planta": "desconocida", "clase": "bloque_grande", "archivo": "clips/ev1202.enc", "iv": "+IrFZwKhIz2SAI3A"}, {"id": "ev1190", "tipo": "evidencia", "fecha": "2026-07-22", "hora": "2026-07-22T08:35:41.530007", "planta": "desconocida", "clase": "bloque_grande", "archivo": "clips/ev1190.enc", "iv": "q5MC9tUCxp1VrXsm"}, {"id": "ev1182", "tipo": "evidencia", "fecha": "2026-07-22", "hora": "2026-07-22T08:23:47.830276", "planta": "desconocida", "clase": "bloque_grande", "archivo": "clips/ev1182.enc", "iv": "ypFyPZqK5fEfCIJj"}]}